addition.py
subtraction.py
easy_math/__init__.py
easy_math/addition.py
easy_math/subtraction.py
python_easy_math-1.0.0.dist-info/LICENSE.md
python_easy_math-1.0.0.dist-info/METADATA
python_easy_math-1.0.0.dist-info/WHEEL
python_easy_math-1.0.0.dist-info/entry_points.txt
python_easy_math-1.0.0.dist-info/top_level.txt
python_easy_math-1.0.0.dist-info/RECORD
