Metadata-Version: 2.1
Name: python-easy-math
Version: 1.0.0
Summary: Python library for basic addition and subtraction of two numbers
Home-page: https://github.com/svpernova09/python-easy-math
Author: Joe Ferguson
Author-email: joe@joeferguson.me
License: MIT
Download-URL: https://github.com/svpernova09/python-easy-math/tarball/1.0.0
Platform: UNKNOWN
Classifier: License :: OSI Approved :: MIT License
Classifier: Topic :: Scientific/Engineering :: Mathematics
Classifier: Topic :: Software Development :: Libraries :: Python Modules
Classifier: Programming Language :: Python :: 3
Classifier: Programming Language :: Python :: 3.5
Classifier: Programming Language :: Python :: 3.6
Classifier: Programming Language :: Python :: 3.7
Classifier: Programming Language :: Python :: Implementation :: CPython
